Workbook

Sheet COMBINED
A1: FDP Form 9 - Statement of Cash Flows
A2: (BLGF Memorandum Circular No. 09 - 2012 dated February 21, 2012, Annex 2)
A4: STATEMENT OF CASH FLOWS
A6: REGION: | D6: REGION VII - CENTRAL VISAYAS | H6: CALENDAR YEAR: | J6: 2026
A7: PROVINCE: | D7: CEBU | H7: QUARTER: | J7: 1
A8: CITY/MUNICIPALITY: | D8: CITY OF CEBU
A10: COMBINED
B12: Cash Flows From Operating Activities:
C13: Cash Inflows:
D14: Collection from Taxpayers | I14: ='GEN FUND'!I15+SEF!I15 -> 4.9055078e+08
D15: Share from Internal Revenue Allotment | I15: ='GEN FUND'!I16 -> 286780899
D16: Receipts from Business/Service Income | I16: ='GEN FUND'!I17 -> 37130513
D17: Collection of Receivables | I17: ='GEN FUND'!I18+'TRUST FUND'!I14 -> 39006
D18: Receipt of Interest Income | I18: ='GEN FUND'!I19+SEF!I16+'TRUST FUND'!I15 -> 17999762
D19: Other Receipts | I19: ='GEN FUND'!I20+SEF!I17+'TRUST FUND'!I16 -> 2.2840339e+08
D20: Adjustments | I20: ='GEN FUND'!I21+SEF!I18+'TRUST FUND'!I17 -> -825196.76
D21: Total Cash Inflow | I21: =SUM(I14:I20) -> 1060079147
C22: Cash Outflows:
D23: Payment of Expenses | I23: ='GEN FUND'!I24+SEF!I21+'TRUST FUND'!I20 -> 5.0293771e+08
D24: Payments to Suppliers / Creditors | I24: ='GEN FUND'!I25+SEF!I22+'TRUST FUND'!I21 -> 1.4634369e+08
D25: Payments to Employees | I25: ='GEN FUND'!I26+SEF!I23+'TRUST FUND'!I22 -> 477905808
D26: Other Disbursements | I26: ='GEN FUND'!I27+SEF!I24+'TRUST FUND'!I23 -> 3.6885716e+08
D27: Adjustments | I27: ='GEN FUND'!I28 -> -68288482
D28: Total Cash Outflow | I28: =SUM(I23:I27) -> 1427755884
C29: Net Cash from Operating Activities | I29: =I21-I28 -> -3.6767674e+08
B31: Cash Flows from Investing Activities
C32: Cash Outflows:
D33: Purchase/Construction of Property, Plant and Equipment Infrastructures
I34: =+'GEN FUND'!I35+SEF!I32+'TRUST FUND'!I31 -> 0
C35: Net Cash from Investing Activities | I35: =-I34 -> 0
A37: Net Increase in Cash | J37: =I29+I35 -> -3.6767674e+08
A38: Cash Balance, December 01, 2025 | J38: ='GEN FUND'!J39+SEF!J37+'TRUST FUND'!J35 -> 9394545011
A39: Cash Balance, Ending December 31, 2025 | J39: =SUM(J37:J38) -> 9026868274
A42: We hereby certify that we have reviewed the contents and hereby attest to the veracity and correctness of the data or information contained in this document.
D45: (sgd.) | I45: (sgd.)
B46: GILBERT L. TABASA, CPA | H46: HON. NESTOR D. ARCHIVAL
B47: Local Accountant | H47: Local Chief Executive
A50: * Cash presented excludes Cash in Bank - Local Currency and Foreign Currency (Time Deposit) as per COA Circular
B51: No. 2020-004 dated January 31, 2020 which explicitly classifies Cash in Bank - Time Deposit under Investments.
A52: * Data presented pertain only to December 2025, as the First Quarter CY 2026 Financial Statements are still in process.

Sheet GEN FUND
A1: FDP Form 9 - Statement of Cash Flows
A2: (BLGF Memorandum Circular No. 09 - 2012 dated February 21, 2012, Annex 2)
A5: STATEMENT OF CASH FLOWS
A7: REGION: | D7: REGION VII - CENTRAL VISAYAS | H7: CALENDAR YEAR: | J7: 2026
A8: PROVINCE: | D8: CEBU | H8: QUARTER: | J8: 1
A9: CITY/MUNICIPALITY: | D9: CITY OF CEBU
A11: GENERAL FUND
B13: Cash Flows From Operating Activities:
C14: Cash Inflows:
D15: Collection from Taxpayers | I15: 3.8265526e+08
D16: Share from Internal Revenue Allotment | I16: 286780899
D17: Receipts from Business/Service Income | I17: 37130513
D18: Collection of Receivables | I18: 37506
D19: Receipt of Interest Income | I19: =10607147.22-53521.28-53521.28 -> 10500105
D20: Other Receipts | I20: 2.0342353e+08
D21: Adjustments | I21: =-409182.51-11194.64-140075.01-258228.25 -> -818680.41
D22: Total Cash Inflow | I22: =SUM(I15:I21) -> 919709137
C23: Cash Outflows:
D24: Payment of Expenses | I24: 4.3742762e+08
D25: Payment to Suppliers / Creditors | I25: 1.4004763e+08
D26: Payments to Employees | I26: 3.9692894e+08
D27: Other Disbursements | I27: 3.6369114e+08
D28: Adjustments | I28: =2789988.71-433705.81-70644764.98 -> -68288482
D29: Total Cash Outflow | I29: =SUM(I24:I28) -> 1269806852
C30: Net Cash from Operating Activities | I30: =I22-I29 -> -3.5009771e+08
B32: Cash Flows from Investing Activities
C33: Cash Outflows:
D34: Purchase/Construction of Property, Plant and Equipment Infrastructures
I35: 0
C36: Net Cash from Investing Activities | I36: =-I35 -> 0
A38: Net Increase in Cash | J38: =I30+I36 -> -3.5009771e+08
A39: Cash Balance, December 01, 2025 | J39: 4.980698e+09
A40: Cash Balance, Ending December 31, 2025 | J40: =SUM(J38:J39) -> 4630600288
A43: We hereby certify that we have reviewed the contents and hereby attest to the veracity and correctness of the data or information contained in this document.
D46: (sgd.) | I46: (sgd.)
B47: GILBERT L. TABASA, CPA | H47: HON. NESTOR D. ARCHIVAL
B48: Local Accountant | H48: Local Chief Executive
A51: * Cash presented excludes Cash in Bank - Local Currency and Foreign Currency (Time Deposit) as per COA Circular
B52: No. 2020-004 dated January 31, 2020 which explicitly classifies Cash in Bank - Time Deposit under Investments.
A53: * Data presented pertain only to December 2025, as the First Quarter CY 2026 Financial Statements are still in process.

Sheet SEF
A1: FDP Form 9 - Statement of Cash Flows
A2: (BLGF Memorandum Circular No. 09 - 2012 dated February 21, 2012, Annex 2)
A5: STATEMENT OF CASH FLOWS
A7: REGION: | D7: REGION VII - CENTRAL VISAYAS | H7: CALENDAR YEAR: | J7: 2026
A8: PROVINCE: | D8: CEBU | H8: QUARTER: | J8: 1
A9: CITY/MUNICIPALITY: | D9: CITY OF CEBU
A11: SPECIAL EDUCATION FUND
B13: Cash Flows From Operating Activities:
C14: Cash Inflows:
D15: Collection from Taxpayers | I15: 1.0789551e+08
D16: Receipt of Interest Income | I16: 6000577.9
D17: Other Receipts | I17: 231000
D18: Adjustments | I18: -17996.41
D19: Total Cash Inflow | I19: =SUM(I15:I18) -> 1.1410909e+08
C20: Cash Outflows:
D21: Payment of Expenses | I21: 6331804.7
D22: Payments to Suppliers/Creditors | I22: 4570655
D23: Payments to Employees | I23: 1998313.4
D24: Other Disbursements | I24: -2789988.7
D25: Adjustments | I25: 0
D26: Total Cash Outflow | I26: =SUM(I21:I25) -> 10110784
C27: Net Cash from Operating Activities | I27: =I19-I26 -> 1.0399831e+08
B29: Cash Flows from Investing Activities
C30: Cash Outflows:
D31: Purchase/Construction of Property, Plant and Equipment Infrastructures
I32: 0
C33: Net Cash from Investing Activities | I33: =-I32 -> 0
A36: Net Increase in Cash | J36: =I27+I33 -> 1.0399831e+08
A37: Cash Balance, December 01, 2025 | J37: 2.2327157e+09
A38: Cash Balance, Ending December 31, 2025 | J38: =SUM(J36:J37) -> 2336714031
A41: We hereby certify that we have reviewed the contents and hereby attest to the veracity and correctness of the data or information contained in this document.
D44: (sgd.) | I44: (sgd.)
B45: GILBERT L. TABASA, CPA | H45: HON. NESTOR D. ARCHIVAL
B46: Local Accountant | H46: Local Chief Executive
A49: * Cash presented excludes Cash in Bank - Local Currency and Foreign Currency (Time Deposit) as per COA Circular
B50: No. 2020-004 dated January 31, 2020 which explicitly classifies Cash in Bank - Time Deposit under Investments.
A51: * Data presented pertain only to December 2025, as the First Quarter CY 2026 Financial Statements are still in process.

Sheet TRUST FUND
A1: FDP Form 9 - Statement of Cash Flows
A2: (BLGF Memorandum Circular No. 09 - 2012 dated February 21, 2012, Annex 2)
A4: STATEMENT OF CASH FLOWS
A6: REGION: | D6: REGION VII - CENTRAL VISAYAS | H6: CALENDAR YEAR: | J6: 2026
A7: PROVINCE: | D7: CEBU | H7: QUARTER: | J7: 1
A8: CITY/MUNICIPALITY: | D8: CITY OF CEBU
A10: TRUST FUND
B12: Cash Flows From Operating Activities:
C13: Cash Inflows:
D14: Collection of Receivables | I14: 1500
D15: Receipt of Interest Income | I15: 1499079.4
D16: Other Receipts | I16: 24748856
D17: Adjustments | I17: =12251.43-771.37 -> 11480.06
D18: Total Cash Inflow | I18: =SUM(I14:I17) -> 26260915
C19: Cash Outflows:
D20: Payment of Expenses | I20: 59178286
D21: Payment to Suppliers/Creditors | I21: 1725401.2
D22: Payments to Employees | I22: 78978550
D23: Other Disbursements | I23: =7968531-12519.94 -> 7956011.1
D24: Adjustments
D25: Total Cash Outflow | I25: =SUM(I20:I24) -> 147838248
C26: Net Cash from Operating Activities | I26: =I18-I25 -> -121577333
B28: Cash Flows From Investing Activities:
C29: Cash Outflows:
D30: Purchase/Construction of Property, Plant & Equipment Infrastructures
I31: 0
C32: Net Cash from Investing Activities | I32: =-I31 -> 0
A34: Net Increase in Cash | J34: =I26+I32 -> -121577333
A35: Cash Balance, December 01, 2025 | J35: 2.1811313e+09
A36: Cash Balance, Ending December 31, 2025 | J36: =SUM(J34:J35) -> 2059553954
A39: We hereby certify that we have reviewed the contents and hereby attest to the veracity and correctness of the data or information contained in this document.
D42: (sgd.) | I42: (sgd.)
B43: GILBERT L. TABASA, CPA | H43: HON. NESTOR D. ARCHIVAL
B44: Local Accountant | H44: Local Chief Executive
A47: * Cash presented excludes Cash in Bank - Local Currency and Foreign Currency (Time Deposit) as per COA Circular
B48: No. 2020-004 dated January 31, 2020 which explicitly classifies Cash in Bank - Time Deposit under Investments.
A49: * Data presented pertain only to December 2025, as the First Quarter CY 2026 Financial Statements are still in process.
